{
  "8121": [
    {
      "index": 1,
      "link": "https://www.lieferando.at/speisekarte/efo-pizza-kebab",
      "i": 0,
      "name": "EFO Pizza & Kebap",
      "logo": "https://res.cloudinary.com/tkwy-prod-eu/image/upload/c_thumb,h_120,w_176/f_auto/q_auto/v1673208793/static-takeaway-com/images/restaurants/at/R5Q0R1QN/logo_465x320",
      "info": [
        "Adresse",
        "Kirchberggasse 3",
        "8121 Deutschfeistritz",
        "Ab 11:00"
      ],
      "meals": {
        "Beliebt": {
          "categoryName": "Beliebt",
          "categoryDescription": "popular meals",
          "items": [
            {
              "name": "Döner Kebap",
              "description": "Döner Kebap\r\nmit Käse\r\nWahl aus: mit Käse, mit Sauce, gemischt, mit Sauce, mild, mit Sauce, scharf, ohne Sauce und mehr.",
              "price": "5,90 €"
            },
            {
              "name": "Pizza Salami",
              "description": "Pizza Salami\r\nmit Salami\r\nWahl aus: mit Ananas, mit Artischocken, mit Blattspinat, mit Champignons, mit Ei und mehr.",
              "price": "10,50 €"
            },
            {
              "name": "Cheeseburger",
              "description": "Cheeseburger\r\nmit 180g reinem, österreichischem Rindfleisch, Cheddar, Salat und Tomaten",
              "price": "9,60 €"
            }
          ]
        },
        "Salate": {
          "categoryName": "Salate",
          "categoryDescription": "Alle Salate werden mit einem Dressing nach Wahl serviert.",
          "items": [
            {
              "name": "Grüner Salat",
              "description": "Grüner Salat\r\nWahl aus: mit Balsamico-Dressing, mit Essig, mit Joghurt-Dressing, mit Kernöl oder ohne Dressing.",
              "price": "6,20 €"
            },
            {
              "name": "Gemischter Salat",
              "description": "Gemischter Salat\r\nWahl aus: mit Balsamico-Dressing, mit Essig, mit Joghurt-Dressing, mit Kernöl oder ohne Dressing.",
              "price": "6,50 €"
            },
            {
              "name": "Tomatensalat",
              "description": "Tomatensalat\r\nWahl aus: mit Balsamico-Dressing, mit Essig, mit Joghurt-Dressing, mit Kernöl oder ohne Dressing.",
              "price": "6,60 €"
            }
          ]
        },
        "Pizza, Ø 33cm": {
          "categoryName": "Pizza, Ø 33cm",
          "categoryDescription": "Alle Pizzen werden mit frischer Tomatensauce, Käse und Oregano zubereitet.",
          "items": [
            {
              "name": "Pizza Margherita",
              "description": "Pizza Margherita\r\nWahl aus: mit Ananas, mit Artischocken, mit Blattspinat, mit Champignons, mit Ei und mehr.",
              "price": "9,70 €"
            },
            {
              "name": "Pizza al Funghi",
              "description": "Pizza al Funghi\r\nmit Champignons\r\nWahl aus: mit Ananas, mit Artischocken, mit Blattspinat, mit Champignons, mit Ei und mehr.",
              "price": "9,90 €"
            },
            {
              "name": "Pizza Mossa Funghi",
              "description": "Pizza Mossa Funghi\r\nmit Schinken und Champignons\r\nWahl aus: mit Ananas, mit Artischocken, mit Blattspinat, mit Champignons, mit Ei und mehr.",
              "price": "10,90 €"
            }
          ]
        },
        "Familienpizza, Ø 60cm": {
          "categoryName": "Familienpizza, Ø 60cm",
          "categoryDescription": "Alle Pizzen werden mit frischer Tomatensauce, Käse und Oregano zubereitet.",
          "items": [
            {
              "name": "Familienpizza",
              "description": "Familienpizza\r\nmit 4 Zutaten nach Wahl\r\nWahl aus: mit Ananas, mit Artischocken, mit Blattspinat, mit Champignons, mit Ei und mehr.",
              "price": "24,10 €"
            }
          ]
        },
        "Pizza-Stangerl": {
          "categoryName": "Pizza-Stangerl",
          "categoryDescription": "",
          "items": [
            {
              "name": "Tonno Stangerl",
              "description": "Tonno Stangerl\r\nmit Thunfisch, Knoblauch und Zwiebeln",
              "price": "9,10 €"
            },
            {
              "name": "Spinat Stangerl",
              "description": "Spinat Stangerl\r\nmit Spinat, Weißkäse und Knoblauch",
              "price": "9,10 €"
            },
            {
              "name": "Salami Stangerl",
              "description": "Salami Stangerl\r\nmit Salami",
              "price": "9,10 €"
            }
          ]
        },
        "Hauptspeisen": {
          "categoryName": "Hauptspeisen",
          "categoryDescription": "",
          "items": [
            {
              "name": "Wiener Schnitzel von der Pute",
              "description": "Wiener Schnitzel von der Pute\r\nmit Pommes frites",
              "price": "9,90 €"
            },
            {
              "name": "Cordon Bleu von der Pute",
              "description": "Cordon Bleu von der Pute\r\nmit Pommes frites",
              "price": "10,50 €"
            },
            {
              "name": "Chicken Wings (6 Stück)",
              "description": "Chicken Wings (6 Stück)",
              "price": "9,00 €"
            }
          ]
        },
        "Pasta": {
          "categoryName": "Pasta",
          "categoryDescription": "Alle Gerichte werden mit einer Nudelsorte nach Wahl zubereitet.",
          "items": [
            {
              "name": "Pasta Gorgonzola",
              "description": "Pasta Gorgonzola\r\nmit Gorgonzola-Rahmsauce\r\nWahl aus: mit Gnocchi, mit Penne, mit Spaghetti, mit Tortellini und extra überbacken.",
              "price": "10,00 €"
            },
            {
              "name": "Pasta Carbonara",
              "description": "Pasta Carbonara\r\nmit Sahnesauce, Ei und einer Zutat nach Wahl\r\nWahl aus: mit Gnocchi, mit Penne, mit Spaghetti, mit Tortellini und extra überbacken.",
              "price": "10,00 €"
            },
            {
              "name": "Pasta Arrabbiata (scharf)",
              "description": "Pasta Arrabbiata (scharf)\r\nmit Tomatensauce, Zwiebeln, Paprika und Oliven\r\nWahl aus: mit Gnocchi, mit Penne, mit Spaghetti, mit Tortellini und extra überbacken.",
              "price": "10,00 €"
            }
          ]
        },
        "Kebap": {
          "categoryName": "Kebap",
          "categoryDescription": "Alle Gerichte werden mit Hühnerfleisch, einer Sauce nach Wahl und Salat zubereitet.",
          "items": [
            {
              "name": "Efo Kebap",
              "description": "Efo Kebap\r\nmit Mais und Käse\r\nWahl aus: mit Käse, mit Sauce, gemischt, mit Sauce, mild, mit Sauce, scharf, ohne Sauce und mehr.",
              "price": "7,00 €"
            },
            {
              "name": "Dürüm",
              "description": "Dürüm\r\nWahl aus: mit Käse, mit Sauce, gemischt, mit Sauce, mild, mit Sauce, scharf, ohne Sauce und mehr.",
              "price": "7,00 €"
            },
            {
              "name": "Kebap Box",
              "description": "Kebap Box\r\nmit Pommes frites, ohne Salat\r\nWahl aus: mit Käse, mit Sauce, gemischt, mit Sauce, mild, mit Sauce, scharf, ohne Sauce und mehr.",
              "price": "8,00 €"
            }
          ]
        },
        "Burger": {
          "categoryName": "Burger",
          "categoryDescription": "",
          "items": [
            {
              "name": "Efo Burger",
              "description": "Efo Burger\r\nmit 180g reinem, österreichischem Rindfleisch, Mozzarella, Rucola, Tomaten, frischen Gurken und Sour Cream",
              "price": "10,50 €"
            },
            {
              "name": "BBQ-Burger",
              "description": "BBQ-Burger\r\nmit 180g reinem, österreichischem Rindfleisch und Barbecuesauce",
              "price": "9,60 €"
            },
            {
              "name": "Hamburger",
              "description": "Hamburger\r\nmit 180g reinem, österreichischem Rindfleisch, Salat, Tomaten, Zwiebeln und Gurken",
              "price": "9,00 €"
            }
          ]
        },
        "Hot Dogs": {
          "categoryName": "Hot Dogs",
          "categoryDescription": "Alle Hot Dogs werden im Pizzateig umhüllt und mit Frankfurter, Ketchup und gerösteten Zwiebeln zubereitet.",
          "items": [
            {
              "name": "Classic Hot Dog",
              "description": "Classic Hot Dog",
              "price": "6,60 €"
            },
            {
              "name": "Royal Hot Dog",
              "description": "Royal Hot Dog\r\nmit knusprig-zartem Speck und Mozzarella",
              "price": "6,60 €"
            },
            {
              "name": "Bacon Hot Dog",
              "description": "Bacon Hot Dog\r\nmit knusprig-zartem Speck",
              "price": "6,90 €"
            }
          ]
        },
        "Beilagen": {
          "categoryName": "Beilagen",
          "categoryDescription": "",
          "items": [
            {
              "name": "Pommes frites",
              "description": "Pommes frites",
              "price": "4,90 €"
            },
            {
              "name": "Potatoe Wedges",
              "description": "Potatoe Wedges",
              "price": "5,40 €"
            },
            {
              "name": "Zwiebelringe (9 Stück)",
              "description": "Zwiebelringe (9 Stück)\r\nmit Dip",
              "price": "5,70 €"
            }
          ]
        },
        "Desserts": {
          "categoryName": "Desserts",
          "categoryDescription": "",
          "items": [
            {
              "name": "Mohr im Hemd",
              "description": "Mohr im Hemd\r\nmit Schokoladensauce",
              "price": "5,60 €"
            },
            {
              "name": "Nuss-Palatschinken",
              "description": "Nuss-Palatschinken",
              "price": "5,90 €"
            },
            {
              "name": "Topfen-Palatschinken",
              "description": "Topfen-Palatschinken",
              "price": "5,90 €"
            }
          ]
        }
      }
    },
    {
      "index": 2,
      "link": "https://www.lieferando.at/speisekarte/number-one",
      "i": 1,
      "name": "Number One",
      "logo": "https://res.cloudinary.com/tkwy-prod-eu/image/upload/c_thumb,h_120,w_176/f_auto/q_auto/v1673208780/static-takeaway-com/images/restaurants/at/OP3NOPPN/logo_465x320",
      "info": [
        "Adresse",
        "Brucker Straße 23 Tür 4",
        "8101 Gratkorn",
        "Ab 11:00"
      ],
      "meals": {
        "Beliebt": {
          "categoryName": "Beliebt",
          "categoryDescription": "popular meals",
          "items": [
            {
              "name": "Kebap im Brot",
              "description": "Kebap im Brot\r\nWahl aus: mit Sauce, mild, mit Sauce, scharf, mit Schafskäse und mit Mais.",
              "price": "5,40 €"
            },
            {
              "name": "Dürüm",
              "description": "Dürüm\r\nWahl aus: mit Sauce, mild, mit Sauce, scharf, mit Schafskäse und mit Mais.",
              "price": "6,40 €"
            },
            {
              "name": "Pizza Salami",
              "description": "Pizza Salami\r\nWahl aus: mit Artischocken, mit Champignons, mit Eiern, mit Gorgonzola, mit Kapern und mehr.",
              "price": "10,90 €"
            }
          ]
        },
        "Salate": {
          "categoryName": "Salate",
          "categoryDescription": "",
          "items": [
            {
              "name": "Grüner Salat",
              "description": "Grüner Salat",
              "price": "4,50 €"
            },
            {
              "name": "Tomatensalat",
              "description": "Tomatensalat",
              "price": "4,50 €"
            },
            {
              "name": "Gemischter Salat",
              "description": "Gemischter Salat",
              "price": "5,00 €"
            }
          ]
        },
        "Pasta": {
          "categoryName": "Pasta",
          "categoryDescription": "Alle Gerichte werden mit einer Nudelsorte nach Wahl zubereitet.",
          "items": [
            {
              "name": "Lasagne al Forno",
              "description": "Lasagne al Forno\r\nmit Fleischsauce und mit Käse überbacken\r\nWahl aus: mit Penne, mit Spaghetti oder mit Tortellini.",
              "price": "8,50 €"
            }
          ]
        },
        "Pizzastangerl": {
          "categoryName": "Pizzastangerl",
          "categoryDescription": "Alle Pizzastangerl werden mit Tomatensauce zubereitet.",
          "items": [
            {
              "name": "Tonno Stangerl",
              "description": "Tonno Stangerl\r\nmit Thunfisch und Zwiebeln",
              "price": "9,50 €"
            },
            {
              "name": "Schinken Stangerl",
              "description": "Schinken Stangerl\r\nmit Schinken und Mais",
              "price": "9,50 €"
            },
            {
              "name": "No1 Stangerl",
              "description": "No1 Stangerl\r\nmit Schinken, Salami und Speck",
              "price": "9,50 €"
            }
          ]
        },
        "Mexikanische Pizza Ø 33cm": {
          "categoryName": "Mexikanische Pizza Ø 33cm",
          "categoryDescription": "Alle Pizzen werden mit Tomatensauce und Käse zubereitet.",
          "items": [
            {
              "name": "Mexikanische Pizza Acapulco",
              "description": "Mexikanische Pizza Acapulco\r\nmit Schinken, Salami, Speck, Jalapenos und Tobasco\r\nWahl aus: mit Artischocken, mit Champignons, mit Eiern, mit Gorgonzola, mit Kapern und mehr.",
              "price": "11,40 €"
            },
            {
              "name": "Mexikanische Pizza Mexico City",
              "description": "Mexikanische Pizza Mexico City\r\nmit Schinken, Champignons, Paprika, Zwiebeln, Jalapenos und Tonasco\r\nWahl aus: mit Artischocken, mit Champignons, mit Eiern, mit Gorgonzola, mit Kapern und mehr.",
              "price": "11,40 €"
            },
            {
              "name": "Mexikanische Pizza Mexicana",
              "description": "Mexikanische Pizza Mexicana\r\nmit Champignons, Mais, Zwiebeln, Paprika, Jalapenos und Tobasco\r\nWahl aus: mit Artischocken, mit Champignons, mit Eiern, mit Gorgonzola, mit Kapern und mehr.",
              "price": "11,40 €"
            }
          ]
        },
        "Mexikanische Partner-Pizza": {
          "categoryName": "Mexikanische Partner-Pizza",
          "categoryDescription": "Alle Pizzen werden mit Tomatensauce und Käse zubereitet.",
          "items": [
            {
              "name": "Mexikanische Partner-Pizza Acapulco",
              "description": "Mexikanische Partner-Pizza Acapulco\r\nmit Schinken, Salami, Speck, Jalapenos und Tobasco\r\nWahl aus: mit Artischocken, mit Champignons, mit Eiern, mit Gorgonzola, mit Kapern und mehr.",
              "price": "15,10 €"
            },
            {
              "name": "Mexikanische Partner-Pizza Mexico City",
              "description": "Mexikanische Partner-Pizza Mexico City\r\nmit Schinken, Champignons, Paprika, Zwiebeln, Jalapenos und Tonasco\r\nWahl aus: mit Artischocken, mit Champignons, mit Eiern, mit Gorgonzola, mit Kapern und mehr.",
              "price": "15,10 €"
            },
            {
              "name": "Mexikanische Partner-Pizza Mexicana",
              "description": "Mexikanische Partner-Pizza Mexicana\r\nmit Champignons, Mais, Zwiebeln, Paprika, Jalapenos und Tobasco\r\nWahl aus: mit Artischocken, mit Champignons, mit Eiern, mit Gorgonzola, mit Kapern und mehr.",
              "price": "15,10 €"
            }
          ]
        },
        "Pizza Ø 33cm": {
          "categoryName": "Pizza Ø 33cm",
          "categoryDescription": "Alle Pizzen werden mit Tomatensauce, Knoblauchrand, Käse und Oregano zubereitet.",
          "items": [
            {
              "name": "Pizza Margherita",
              "description": "Pizza Margherita\r\nWahl aus: mit Artischocken, mit Champignons, mit Eiern, mit Gorgonzola, mit Kapern und mehr.",
              "price": "9,90 €"
            },
            {
              "name": "Pizza al Funghi",
              "description": "Pizza al Funghi\r\nmit Champignons\r\nWahl aus: mit Artischocken, mit Champignons, mit Eiern, mit Gorgonzola, mit Kapern und mehr.",
              "price": "10,90 €"
            },
            {
              "name": "Pizza Salami",
              "description": "Pizza Salami\r\nWahl aus: mit Artischocken, mit Champignons, mit Eiern, mit Gorgonzola, mit Kapern und mehr.",
              "price": "10,90 €"
            }
          ]
        },
        "Partner-Pizza": {
          "categoryName": "Partner-Pizza",
          "categoryDescription": "Alle Pizzen werden mit Tomatensauce, Knoblauchrand, Käse und Oregano zubereitet.",
          "items": [
            {
              "name": "Partner-Pizza Margherita",
              "description": "Partner-Pizza Margherita\r\nWahl aus: mit Artischocken, mit Champignons, mit Eiern, mit Gorgonzola, mit Kapern und mehr.",
              "price": "13,40 €"
            },
            {
              "name": "Partner-Pizza al Funghi",
              "description": "Partner-Pizza al Funghi\r\nmit Champignons\r\nWahl aus: mit Artischocken, mit Champignons, mit Eiern, mit Gorgonzola, mit Kapern und mehr.",
              "price": "14,40 €"
            },
            {
              "name": "Partner-Pizza Salami",
              "description": "Partner-Pizza Salami\r\nWahl aus: mit Artischocken, mit Champignons, mit Eiern, mit Gorgonzola, mit Kapern und mehr.",
              "price": "14,40 €"
            }
          ]
        },
        "Familienpizza": {
          "categoryName": "Familienpizza",
          "categoryDescription": "Alle Pizzen werden mit Tomatensauce, Knoblauchrand, Käse und Oregano zubereitet.",
          "items": [
            {
              "name": "Familienpizza",
              "description": "Familienpizza\r\nmit 5 Zutaten nach Wahl\r\nWahl aus: mit Ananas, mit Artischocken, mit Champignons, mit Ei, mit Eisbergsalat und mehr.",
              "price": "21,90 €"
            }
          ]
        },
        "Kebap und Co": {
          "categoryName": "Kebap und Co",
          "categoryDescription": "",
          "items": [
            {
              "name": "Kebap im Brot",
              "description": "Kebap im Brot\r\nWahl aus: mit Sauce, mild, mit Sauce, scharf, mit Schafskäse und mit Mais.",
              "price": "5,40 €"
            },
            {
              "name": "Kebap mit Käse",
              "description": "Kebap mit Käse\r\nWahl aus: mit Sauce, mild, mit Sauce, scharf, mit Schafskäse und mit Mais.",
              "price": "6,40 €"
            },
            {
              "name": "Vegetarisches Kebap",
              "description": "Vegetarisches Kebap\r\nWahl aus: mit Sauce, mild, mit Sauce, scharf, mit Schafskäse und mit Mais.",
              "price": "4,50 €"
            }
          ]
        },
        "Burger": {
          "categoryName": "Burger",
          "categoryDescription": "Alle Burger werden mit einer 180g österreichischem Rindfleisch zubereitet und mit Pommes frites serviert.",
          "items": [
            {
              "name": "Hamburger",
              "description": "Hamburger\r\nmit Tomaten, Salat, Zwiebeln und Haussauce\r\nWahl aus: mit Barbcesauce, mit Haussauce, mit Hot-Chilisauce, mit Ketchup, mit Mayonnaise und mehr.",
              "price": "10,90 €"
            },
            {
              "name": "Cheeseburger",
              "description": "Cheeseburger\r\nmit Cheddar, Tomaten, Salat, Zwiebeln und Haussauce\r\nWahl aus: mit Barbcesauce, mit Haussauce, mit Hot-Chilisauce, mit Ketchup, mit Mayonnaise und mehr.",
              "price": "10,90 €"
            },
            {
              "name": "Mexiko Burger",
              "description": "Mexiko Burger\r\nmit Jalapenos, Tomaten, Salat, Zwiebeln und Hot-Chilisauce\r\nWahl aus: mit Barbcesauce, mit Haussauce, mit Hot-Chilisauce, mit Ketchup, mit Mayonnaise und mehr.",
              "price": "11,90 €"
            }
          ]
        },
        "Dessert": {
          "categoryName": "Dessert",
          "categoryDescription": "",
          "items": [
            {
              "name": "Topfen-Palatschinken",
              "description": "Topfen-Palatschinken",
              "price": "4,60 €"
            },
            {
              "name": "Muss-Palatschinken",
              "description": "Muss-Palatschinken",
              "price": "4,60 €"
            },
            {
              "name": "Mohr im Hemd",
              "description": "Mohr im Hemd",
              "price": "4,60 €"
            }
          ]
        }
      }
    },
    {
      "index": 3,
      "link": "https://www.lieferando.at/speisekarte/pizzeria-latiano-restaurant",
      "i": 2,
      "name": "Pizzeria Latiano Restaurant",
      "logo": "https://res.cloudinary.com/tkwy-prod-eu/image/upload/c_thumb,h_120,w_176/f_auto/q_auto/v1673343573/static-takeaway-com/images/restaurants/at/R155O5QN/logo_465x320",
      "info": [
        "Adresse",
        "Bahnhofstraße 38A",
        "8112 Gemeinde Gratwein",
        "Ab 10:45"
      ],
      "meals": {
        "Beliebt": {
          "categoryName": "Beliebt",
          "categoryDescription": "popular meals",
          "items": [
            {
              "name": "Spaghetti alla Carbonara",
              "description": "Spaghetti alla Carbonara\r\nmit Obers, Pancetta und Ei",
              "price": "10,50 €"
            },
            {
              "name": "Pizza Milano",
              "description": "Pizza Milano\r\nmit milder Salami\r\nWahl aus: mit Ananas, mit Artischocken, mit Büffelmozzarella, mit Champignons, mit Ei und mehr.",
              "price": "10,40 €"
            },
            {
              "name": "Burger Menü",
              "description": "Burger Menü\r\n• 1 Burger nach Wahl\r\n• 1 Pommes frites\r\n• 1 Getränk 0,33l nach Wahl\r\nWahl aus: mit Cheeseburger, XL, mit Chili Cheeseburger, XL, mit Hamburger, XL, Coca-Cola 0,33l (EINWEG), Coca-Cola Zero Sugar 0,33l (EINWEG) und mehr.",
              "price": "14,50 €"
            }
          ]
        },
        "Menüs": {
          "categoryName": "Menüs",
          "categoryDescription": "",
          "items": [
            {
              "name": "Burger Menü",
              "description": "Burger Menü\r\n• 1 Burger nach Wahl\r\n• 1 Pommes frites\r\n• 1 Getränk 0,33l nach Wahl\r\nWahl aus: mit Cheeseburger, XL, mit Chili Cheeseburger, XL, mit Hamburger, XL, Coca-Cola 0,33l (EINWEG), Coca-Cola Zero Sugar 0,33l (EINWEG) und mehr.",
              "price": "14,50 €"
            }
          ]
        },
        "Suppen": {
          "categoryName": "Suppen",
          "categoryDescription": "",
          "items": [
            {
              "name": "Zuppa di Pomodoro",
              "description": "Zuppa di Pomodoro\r\nmit Grana Padano",
              "price": "5,90 €"
            }
          ]
        },
        "Insalate": {
          "categoryName": "Insalate",
          "categoryDescription": "Alle Salate werden mit einem Dressing nach Wahl zubereitet.",
          "items": [
            {
              "name": "Insalata di Rucola e Grana",
              "description": "Insalata di Rucola e Grana\r\nmit Rucola, Kirschtomaten und Grana\r\nWahl aus: mit Essig, mit Joghurt-Dressing oder ohne Dressing.",
              "price": "6,90 €"
            },
            {
              "name": "Insalata Mista",
              "description": "Insalata Mista\r\ngemischter Salat\r\nWahl aus: mit Essig, mit Joghurt-Dressing oder ohne Dressing.",
              "price": "4,90 €"
            },
            {
              "name": "Cesar Salat",
              "description": "Cesar Salat\r\nBlattsalat mit gegrillten Hühnerbruststreifen, Kirschtomaten, Grana, Weißbrot-Croutons und Ceasar Dressing\r\nWahl aus: mit Essig, mit Joghurt-Dressing oder ohne Dressing.",
              "price": "11,40 €"
            }
          ]
        },
        "Pizza, Ø 33cm": {
          "categoryName": "Pizza, Ø 33cm",
          "categoryDescription": "",
          "items": [
            {
              "name": "Pizza Margherita",
              "description": "Pizza Margherita\r\nWahl aus: mit Ananas, mit Artischocken, mit Büffelmozzarella, mit Champignons, mit Ei und mehr.",
              "price": "9,40 €"
            },
            {
              "name": "Pizza Al Funghi",
              "description": "Pizza Al Funghi\r\nmit Champignons\r\nWahl aus: mit Ananas, mit Artischocken, mit Büffelmozzarella, mit Champignons, mit Ei und mehr.",
              "price": "10,40 €"
            },
            {
              "name": "Pizza Mossa Funghi",
              "description": "Pizza Mossa Funghi\r\nmit Schinken und Champignons\r\nWahl aus: mit Ananas, mit Artischocken, mit Büffelmozzarella, mit Champignons, mit Ei und mehr.",
              "price": "10,40 €"
            }
          ]
        },
        "Pizza, Ø 40cm": {
          "categoryName": "Pizza, Ø 40cm",
          "categoryDescription": "",
          "items": [
            {
              "name": "Pizza Margherita",
              "description": "Pizza Margherita\r\nWahl aus: mit Ananas, mit Artischocken, mit Büffelmozzarella, mit Champignons, mit Ei und mehr.",
              "price": "12,90 €"
            },
            {
              "name": "Pizza Al Funghi",
              "description": "Pizza Al Funghi\r\nmit Champignons\r\nWahl aus: mit Ananas, mit Artischocken, mit Büffelmozzarella, mit Champignons, mit Ei und mehr.",
              "price": "13,90 €"
            },
            {
              "name": "Pizza Mossa Funghi",
              "description": "Pizza Mossa Funghi\r\nmit Schinken und Champignons\r\nWahl aus: mit Ananas, mit Artischocken, mit Büffelmozzarella, mit Champignons, mit Ei und mehr.",
              "price": "13,90 €"
            }
          ]
        },
        "Pasta": {
          "categoryName": "Pasta",
          "categoryDescription": "",
          "items": [
            {
              "name": "Spaghetti alla Bolognese",
              "description": "Spaghetti alla Bolognese\r\nmit würzigem Rinderragout",
              "price": "10,40 €"
            },
            {
              "name": "Spaghetti Aglio e Peperoncino",
              "description": "Spaghetti Aglio e Peperoncino\r\nmit Knoblauch, Chili und Olivenöl",
              "price": "8,90 €"
            },
            {
              "name": "Spaghetti alla Carbonara",
              "description": "Spaghetti alla Carbonara\r\nmit Obers, Pancetta und Ei",
              "price": "10,50 €"
            }
          ]
        },
        "Hauptspeisen": {
          "categoryName": "Hauptspeisen",
          "categoryDescription": "",
          "items": [
            {
              "name": "Wienerschnitzel",
              "description": "Wienerschnitzel\r\nvom Huhn mit Pommes frites",
              "price": "9,90 €"
            },
            {
              "name": "Gyros",
              "description": "Gyros\r\ngegrilltes Hühnerfilet mit Zwiebel und Paprika, dazu hausgemachtes Parmesan und Pizzabrot",
              "price": "12,40 €"
            },
            {
              "name": "Nuggets (9 Stück)",
              "description": "Nuggets (9 Stück)\r\nmit Pommes frites",
              "price": "9,90 €"
            }
          ]
        },
        "Burger, XL": {
          "categoryName": "Burger, XL",
          "categoryDescription": "Alle Burger werden mit 180g Rindfleisch-Patty zubereitet und mit Pommes frites serviert.",
          "items": [
            {
              "name": "Chili Cheeseburger XL",
              "description": "Chili Cheeseburger XL\r\nmit Salat, Tomaten, Balsamico-Zwiebeln, Cheddar, scharfe Pfefferoni und hausgemachter Aioli",
              "price": "10,90 €"
            },
            {
              "name": "Hamburger XL",
              "description": "Hamburger XL\r\nmit Salat, Tomaten, Balsamico-Zwiebeln und hausgemachter Aioli",
              "price": "10,90 €"
            },
            {
              "name": "Cheeseburger XL",
              "description": "Cheeseburger XL\r\nmit Salat, Tomaten, Balsamico-Zwiebeln, Cheddar und hausgemachter Aioli",
              "price": "10,90 €"
            }
          ]
        },
        "Burger, XXL": {
          "categoryName": "Burger, XXL",
          "categoryDescription": "Alle Burger werden mit 360g Rindfleisch-Patty zubereitet und mit Pommes frites serviert.",
          "items": [
            {
              "name": "Chili Cheeseburger XXL",
              "description": "Chili Cheeseburger XXL\r\nmit Salat, Tomaten, Balsamico-Zwiebeln, Cheddar, scharfe Pfefferoni und hausgemachter Aioli",
              "price": "15,00 €"
            },
            {
              "name": "Hamburger XXL",
              "description": "Hamburger XXL\r\nmit Salat, Tomaten, Balsamico-Zwiebeln und hausgemachter Aioli",
              "price": "15,00 €"
            },
            {
              "name": "Cheeseburger XXL",
              "description": "Cheeseburger XXL\r\nmit Salat, Tomaten, Balsamico-Zwiebeln, Cheddar und hausgemachter Aioli",
              "price": "15,00 €"
            }
          ]
        },
        "Kindergerichte": {
          "categoryName": "Kindergerichte",
          "categoryDescription": "",
          "items": [
            {
              "name": "Pizza Couere",
              "description": "Pizza Couere\r\nmit Tomatensauce und Mozzarella",
              "price": "5,90 €"
            },
            {
              "name": "Pizza Sole",
              "description": "Pizza Sole\r\nmit Tomatensauce, Mozzarella, Schinken und Ananas",
              "price": "6,40 €"
            },
            {
              "name": "Pizza Mickey Mouse",
              "description": "Pizza Mickey Mouse\r\nmit Tomatensauce, Mozzarella, Salami und Mais",
              "price": "6,40 €"
            }
          ]
        },
        "Beilagen": {
          "categoryName": "Beilagen",
          "categoryDescription": "",
          "items": [
            {
              "name": "Pommes frites",
              "description": "Pommes frites",
              "price": "2,90 €"
            },
            {
              "name": "Bratkartoffeln",
              "description": "Bratkartoffeln",
              "price": "2,90 €"
            },
            {
              "name": "Petersilienkartoffeln",
              "description": "Petersilienkartoffeln",
              "price": "3,40 €"
            }
          ]
        },
        "Dessert": {
          "categoryName": "Dessert",
          "categoryDescription": "",
          "items": [
            {
              "name": "Profiteroles",
              "description": "Profiteroles\r\nBrandteigkrapfen gefüllt mit Schlagobers und Schokosauce, dazu Vanillecreme",
              "price": "5,20 €"
            }
          ]
        }
      }
    },
    {
      "index": 4,
      "link": "https://www.lieferando.at/speisekarte/pizzeria-carolina",
      "i": 3,
      "name": "Pizzeria Carolina",
      "logo": "https://res.cloudinary.com/tkwy-prod-eu/image/upload/c_thumb,h_120,w_176/f_auto/q_auto/v1673208644/static-takeaway-com/images/restaurants/at/5N1NPN3/logo_465x320",
      "info": [
        "Adresse",
        "Dr.Karl Renner-Straße 1 b",
        "8101 Kirchenviertel",
        "Ab 11:00"
      ],
      "meals": {
        "Beliebt": {
          "categoryName": "Beliebt",
          "categoryDescription": "popular meals",
          "items": [
            {
              "name": "Spaghetti Carbonara",
              "description": "Spaghetti Carbonara\r\nmit Schinken, Rahmsauce und Knoblauch",
              "price": "10,50 €"
            },
            {
              "name": "Pizza Margherita",
              "description": "Pizza Margherita\r\nWahl aus: mit Ananas, mit Artischocken, mit Basilikum, mit Champignons, mit Ei und mehr.",
              "price": "10,50 €"
            },
            {
              "name": "Tagliatelle Bolognese",
              "description": "Tagliatelle Bolognese\r\nmit Bolognesesauce",
              "price": "10,50 €"
            }
          ]
        },
        "Menüs": {
          "categoryName": "Menüs",
          "categoryDescription": "Alle Menüs werden mit Coca-Cola 0,33l serviert.",
          "items": [
            {
              "name": "Burger-Menü 1",
              "description": "Burger-Menü 1\r\n• 1 Burger nach Wahl\r\n• 1 Pommes frites\r\nWahl aus: Carolina Burger, Cheeseburger, Griechischer Burger, Hawaii Burger, Italia Burger und mehr.",
              "price": "14,50 €"
            },
            {
              "name": "Pizza-Menü 1",
              "description": "Pizza-Menü 1\r\n• 1 Pizza (Ø 33cm) nach Wahl\r\n• 1 kleiner gemischter Salat\r\nWahl aus: Calzone, Pizza a la Casa, Pizza al Mare, Pizza Americana, Pizza Boscaiola und mehr.",
              "price": "14,50 €"
            }
          ]
        },
        "Pizzatag": {
          "categoryName": "Pizzatag",
          "categoryDescription": "Alle Pizzen werden mit Getränk 0,33l nach Wahl serviert.",
          "items": [
            {
              "name": "Pizza Margherita",
              "description": "Pizza Margherita\r\nWahl aus: mit Ananas, mit Artischocken, mit Basilikum, mit Champignons, mit Ei und mehr.",
              "price": "10,50 €"
            },
            {
              "name": "Pizza con Salami",
              "description": "Pizza con Salami\r\nmit Salami\r\nWahl aus: mit Ananas, mit Artischocken, mit Basilikum, mit Champignons, mit Ei und mehr.",
              "price": "10,50 €"
            },
            {
              "name": "Pizza Al Mare",
              "description": "Pizza Al Mare\r\nmit Meeresfrüchten\r\nWahl aus: mit Ananas, mit Artischocken, mit Basilikum, mit Champignons, mit Ei und mehr.",
              "price": "10,50 €"
            }
          ]
        },
        "Salate": {
          "categoryName": "Salate",
          "categoryDescription": "Alle Salate werden mit einem Dressing nach Wahl serviert.",
          "items": [
            {
              "name": "Grüner Salat",
              "description": "Grüner Salat\r\nWahl aus: mit Balsamico-Dressing, mit Kernöl, mit Kräuter-Dressing oder ohne Dressing.",
              "price": "3,50 €"
            },
            {
              "name": "Kartoffelsalat",
              "description": "Kartoffelsalat\r\nWahl aus: mit Balsamico-Dressing, mit Kernöl, mit Kräuter-Dressing oder ohne Dressing.",
              "price": "3,50 €"
            },
            {
              "name": "Gemischter Salat",
              "description": "Gemischter Salat\r\nnach Saison\r\nWahl aus: mit Balsamico-Dressing, mit Kernöl, mit Kräuter-Dressing oder ohne Dressing.",
              "price": "3,50 €"
            }
          ]
        },
        "Pasta": {
          "categoryName": "Pasta",
          "categoryDescription": "Alle Nudelgerichte werden mit grünem Salat serviert.",
          "items": [
            {
              "name": "Spaghetti Bolognese",
              "description": "Spaghetti Bolognese\r\nmit grünem Salat",
              "price": "10,50 €"
            },
            {
              "name": "Spaghetti Santorin",
              "description": "Spaghetti Santorin\r\nmit grünem Salat",
              "price": "10,50 €"
            },
            {
              "name": "Spaghetti Carbonara",
              "description": "Spaghetti Carbonara\r\nmit Schinken, Rahmsauce und Knoblauch",
              "price": "10,50 €"
            }
          ]
        },
        "Pizza, Ø 33cm": {
          "categoryName": "Pizza, Ø 33cm",
          "categoryDescription": "Alle Pizzen werden mit Käse, Tomatensauce und Oregano zubereitet.",
          "items": [
            {
              "name": "Pizza Margherita",
              "description": "Pizza Margherita\r\nWahl aus: mit Ananas, mit Artischocken, mit Basilikum, mit Champignons, mit Ei und mehr.",
              "price": "10,50 €"
            },
            {
              "name": "Pizza con Salami",
              "description": "Pizza con Salami\r\nmit Salami\r\nWahl aus: mit Ananas, mit Artischocken, mit Basilikum, mit Champignons, mit Ei und mehr.",
              "price": "10,50 €"
            },
            {
              "name": "Pizza al Mare",
              "description": "Pizza al Mare\r\nmit Meeresfrüchten\r\nWahl aus: mit Ananas, mit Artischocken, mit Basilikum, mit Champignons, mit Ei und mehr.",
              "price": "10,50 €"
            }
          ]
        },
        "Pizzastangerl": {
          "categoryName": "Pizzastangerl",
          "categoryDescription": "",
          "items": [
            {
              "name": "Pizzastangerl Mozzarella",
              "description": "Pizzastangerl Mozzarella\r\nmit Mozzarella und Basilikum\r\nWahl aus: mit Ananas, mit Artischocken, mit Basilikum, mit Champignons, mit Ei und mehr.",
              "price": "8,50 €"
            },
            {
              "name": "Pizzastangerl Florentina",
              "description": "Pizzastangerl Florentina\r\nmit Pizzaschinken\r\nWahl aus: mit Ananas, mit Artischocken, mit Basilikum, mit Champignons, mit Ei und mehr.",
              "price": "8,50 €"
            },
            {
              "name": "Pizzastangerl Salami",
              "description": "Pizzastangerl Salami\r\nWahl aus: mit Ananas, mit Artischocken, mit Basilikum, mit Champignons, mit Ei und mehr.",
              "price": "8,50 €"
            }
          ]
        },
        "Burger": {
          "categoryName": "Burger",
          "categoryDescription": "",
          "items": [
            {
              "name": "Italia Burger",
              "description": "Italia Burger\r\nmit Blattsalat, Tomaten, Mozzarella und Rucola",
              "price": "6,00 €"
            },
            {
              "name": "Hawaii Burger",
              "description": "Hawaii Burger\r\nmit Blattsalat, Tomaten, Ananasscheiben und Schinken",
              "price": "6,00 €"
            },
            {
              "name": "Steirer Burger",
              "description": "Steirer Burger\r\nmit Blattsalat, Tomaten, Speck, Zwiebeln und Ei",
              "price": "6,00 €"
            }
          ]
        },
        "Himmlische Speisen": {
          "categoryName": "Himmlische Speisen",
          "categoryDescription": "",
          "items": [
            {
              "name": "Hühner Nuggets (8 Stück)",
              "description": "Hühner Nuggets (8 Stück)\r\nmit Pommes frites und Ketchup",
              "price": "10,50 €"
            },
            {
              "name": "Gebackenes Schnitzel von Schwein",
              "description": "Gebackenes Schnitzel von Schwein\r\nmit Pommes frites",
              "price": "10,50 €"
            },
            {
              "name": "Gebackenes Schnitzel von Huhn",
              "description": "Gebackenes Schnitzel von Huhn\r\nmit Pommes frites",
              "price": "10,50 €"
            }
          ]
        },
        "Beilagen und Saucen": {
          "categoryName": "Beilagen und Saucen",
          "categoryDescription": "",
          "items": [
            {
              "name": "Pommes frites",
              "description": "Pommes frites\r\nmit Ketchup",
              "price": "3,50 €"
            },
            {
              "name": "Potato Wedges",
              "description": "Potato Wedges\r\nmit Knoblauchsauce",
              "price": "3,50 €"
            },
            {
              "name": "Pitabrot",
              "description": "Pitabrot",
              "price": "2,50 €"
            }
          ]
        },
        "Desserts": {
          "categoryName": "Desserts",
          "categoryDescription": "",
          "items": [
            {
              "name": "Tiramisu",
              "description": "Tiramisu",
              "price": "3,50 €"
            },
            {
              "name": "Mohr im Hemd",
              "description": "Mohr im Hemd",
              "price": "3,90 €"
            }
          ]
        }
      }
    },
    {
      "index": 5,
      "link": "https://www.lieferando.at/speisekarte/click-clack-coffee-kitchen",
      "i": 4,
      "name": "Click Clack coffee & kitchen",
      "logo": "https://res.cloudinary.com/tkwy-prod-eu/image/upload/c_thumb,h_120,w_176/f_auto/q_auto/v1673208786/static-takeaway-com/images/restaurants/at/33Q00O7N/logo_465x320",
      "info": [
        "Adresse",
        "Bahnhofplatz 3",
        "8112 Gratwein-Straßengel",
        "Ab 11:00"
      ],
      "meals": {
        "Beliebt": {
          "categoryName": "Beliebt",
          "categoryDescription": "popular meals",
          "items": [
            {
              "name": "A Classic Caesar Salad",
              "description": "A Classic Caesar Salad\r\nmit Croutons, Parmigiano und Caesar-Dressing\r\nWahl aus: mit Garnelen, gebraten, mit Hühnerfiletstreifen, gebacken, mit Hühnerfiletstreifen, gebraten und ohne Dressing.",
              "price": "10,90 €"
            },
            {
              "name": "Hausgemachte Fries",
              "description": "Hausgemachte Fries",
              "price": "4,80 €"
            },
            {
              "name": "Cheeseburger Menü",
              "description": "Cheeseburger Menü\r\n1 Cheeseburger, 1 hausgemachte Fries, 1 Coleslaw (klein), 1 Dip nach Wahl\r\nWahl aus: mit Barbecuesauce, mit Cocktailsauce, mit Ketchup, mit Sour Cream, mit Spicy-Mayonnaise und mehr.",
              "price": "19,10 €"
            }
          ]
        },
        "Menüs": {
          "categoryName": "Menüs",
          "categoryDescription": "",
          "items": [
            {
              "name": "Italian Nights",
              "description": "Italian Nights\r\nAntipasti-Combo (klein), 2 Nudelgerichte nach Wahl, 2 Tiramisu, 1 Prosecco Bortolotti Docg 0,7l\r\nWahl aus: Lasagne Classico, Linguine Basilikum-Pesto, Linguine Gamberetti, Spaghetti Aglio Olio e Peperonicino, Spaghetti Pomodoro e Basilico und mehr.",
              "price": "55,00 €"
            },
            {
              "name": "Burger-Love",
              "description": "Burger-Love\r\n2 Burger nach Wahl, hausgemachte Fries, Coleslaw, 1 Dip nach Wahl, 2 Kuchen nach Wahl, 2 Getränke nach Wahl\r\nWahl aus: BBQ-Burger, Blue-Chesse Burger, Caprese Burger, Cheeseburger, Ckick-Clack Burger und mehr.",
              "price": "46,00 €"
            },
            {
              "name": "Click-Clacks Choice",
              "description": "Click-Clacks Choice\r\nAntipasti-Combo (groß), 2 Burger nach Wahl, hausgemachte Fries, Coleslaw, Dip nach Wahl, 2 Kuchen nach Wahl, 1 gelber Muskateller, Brolli Südsteiermark 0,7l\r\nWahl aus: BBQ-Burger, Blue-Chesse Burger, Caprese Burger, Cheeseburger, Ckick-Clack Burger und mehr.",
              "price": "65,00 €"
            }
          ]
        },
        "Starters": {
          "categoryName": "Starters",
          "categoryDescription": "",
          "items": [
            {
              "name": "Garnelen in Olivenöl",
              "description": "Garnelen in Olivenöl\r\ngebraten mit Chili und Knoblauch, dazu Focaccia-Brot",
              "price": "12,90 €"
            },
            {
              "name": "Chicken Fingers",
              "description": "Chicken Fingers\r\nmit einem Dip nach Wahl\r\nWahl aus: mit Barbecuesauce, mit Cocktailsauce, mit Ketchup, mit Sour Cream, mit Spicy-Mayonnaise und mehr.",
              "price": "9,90 €"
            },
            {
              "name": "Zitronen-Hummus klein",
              "description": "Zitronen-Hummus klein\r\nmit gebratenem Gemüse, dazu Pita-Brot",
              "price": "4,90 €"
            }
          ]
        },
        "Salads - Bowls": {
          "categoryName": "Salads - Bowls",
          "categoryDescription": "",
          "items": [
            {
              "name": "A Classic Caesar Salad",
              "description": "A Classic Caesar Salad\r\nmit Croutons, Parmigiano und Caesar-Dressing\r\nWahl aus: mit Garnelen, gebraten, mit Hühnerfiletstreifen, gebacken, mit Hühnerfiletstreifen, gebraten und ohne Dressing.",
              "price": "10,90 €"
            },
            {
              "name": "Pumpkin Red Beet-Bowl",
              "description": "Pumpkin Red Beet-Bowl\r\nmit Quinoa, Blattsalat, Kürbis, Gurken, Tomate, rote Rübe, Sojabohnen und Joghurt-Dressing\r\nWahl aus: mit Garnelen, gebraten, mit Hühnerfiletstreifen, gebacken, mit Hühnerfiletstreifen, gebraten und ohne Dressing.",
              "price": "11,90 €"
            },
            {
              "name": "Mango-Avocado Bowl",
              "description": "Mango-Avocado Bowl\r\nmit Quinoa, Teriyaki, Blattsalat, Nüsse, Avocado, Mango, Karotte, Oliven, Sojabohnen und Joghurt-Dressing\r\nWahl aus: mit Garnelen, gebraten, mit Hühnerfiletstreifen, gebacken, mit Hühnerfiletstreifen, gebraten und ohne Dressing.",
              "price": "12,30 €"
            }
          ]
        },
        "Pasta e Basta": {
          "categoryName": "Pasta e Basta",
          "categoryDescription": "",
          "items": [
            {
              "name": "Spaghetti Pomodoro e Basilico",
              "description": "Spaghetti Pomodoro e Basilico\r\nmit Tomatensauce und Basilikum",
              "price": "10,50 €"
            },
            {
              "name": "Lasagne Classico",
              "description": "Lasagne Classico\r\nmit Bolognese",
              "price": "12,70 €"
            },
            {
              "name": "Linguine Basilikum-Pesto",
              "description": "Linguine Basilikum-Pesto\r\nmit Pesto aus Basilikum, Oliven, Gewürzen, Grana und Pinienkernen",
              "price": "11,90 €"
            }
          ]
        },
        "Tasty Burgers": {
          "categoryName": "Tasty Burgers",
          "categoryDescription": "Alle Burger werden im Bäcker-Bun zubereitet.",
          "items": [
            {
              "name": "Hamburger",
              "description": "Hamburger\r\nmit Rindfleisch-Patty, Burgersauce, Zwiebeln und Essiggurkerl",
              "price": "12,90 €"
            },
            {
              "name": "Cheeseburger",
              "description": "Cheeseburger\r\nmit Rindfleisch-Patty, Cheddar, Salat, Zwiebeln, Tomaten und Burgersauce",
              "price": "13,90 €"
            },
            {
              "name": "BBQ-Burger",
              "description": "BBQ-Burger\r\nmit Rindfleisch-Patty, Cheddar, Tomate, Salat, Schmor-Zwiebeln, Speck und Barbecuesauce",
              "price": "14,50 €"
            }
          ]
        },
        "Tasty Burger Menü": {
          "categoryName": "Tasty Burger Menü",
          "categoryDescription": "",
          "items": [
            {
              "name": "Hamburger Menü",
              "description": "Hamburger Menü\r\n1 Hamburger, 1 hausgemachte Fries, 1 Coleslaw (klein), 1 Dip nach Wahl\r\nWahl aus: mit Barbecuesauce, mit Cocktailsauce, mit Ketchup, mit Sour Cream, mit Spicy-Mayonnaise und mehr.",
              "price": "18,10 €"
            },
            {
              "name": "Cheeseburger Menü",
              "description": "Cheeseburger Menü\r\n1 Cheeseburger, 1 hausgemachte Fries, 1 Coleslaw (klein), 1 Dip nach Wahl\r\nWahl aus: mit Barbecuesauce, mit Cocktailsauce, mit Ketchup, mit Sour Cream, mit Spicy-Mayonnaise und mehr.",
              "price": "19,10 €"
            },
            {
              "name": "BBQ-Burger Menü",
              "description": "BBQ-Burger Menü\r\n1 BBQ-Burger, 1 hausgemachte Fries, 1 Coleslaw (klein), 1 Dip nach Wahl\r\nWahl aus: mit Barbecuesauce, mit Cocktailsauce, mit Ketchup, mit Sour Cream, mit Spicy-Mayonnaise und mehr.",
              "price": "19,70 €"
            }
          ]
        },
        "Snacks - Saucen": {
          "categoryName": "Snacks - Saucen",
          "categoryDescription": "",
          "items": [
            {
              "name": "Schinken-Käse-Toast",
              "description": "Schinken-Käse-Toast\r\nmit Ketchup",
              "price": "5,40 €"
            },
            {
              "name": "Heiße Focaccia",
              "description": "Heiße Focaccia\r\nmit Schinken und Käse",
              "price": "6,50 €"
            },
            {
              "name": "Ketchup",
              "description": "Ketchup",
              "price": "1,20 €"
            }
          ]
        },
        "Desserts": {
          "categoryName": "Desserts",
          "categoryDescription": "",
          "items": [
            {
              "name": "Tiramisu",
              "description": "Tiramisu",
              "price": "5,90 €"
            },
            {
              "name": "Mamorgugelhupf",
              "description": "Mamorgugelhupf",
              "price": "4,20 €"
            },
            {
              "name": "Eierlikörkuchen",
              "description": "Eierlikörkuchen",
              "price": "4,20 €"
            }
          ]
        }
      }
    },
    {
      "index": 6,
      "link": "https://www.lieferando.at/speisekarte/bellissimo-xxl-hauptplatz",
      "i": 5,
      "name": "Bellissimo XXL Hauptplatz",
      "logo": "https://res.cloudinary.com/tkwy-prod-eu/image/upload/c_thumb,h_120,w_176/f_auto/q_auto/v1673381852/static-takeaway-com/images/restaurants/at/OQR1OON1/logo_465x320",
      "info": [
        "Adresse",
        "Hauptplatz 15",
        "8130 Frohnleiten",
        "Ab 11:00"
      ],
      "meals": {
        "Beliebt": {
          "categoryName": "Beliebt",
          "categoryDescription": "popular meals",
          "items": [
            {
              "name": "Tiramisu",
              "description": "Tiramisu",
              "price": "4,50 €"
            },
            {
              "name": "Mohr im Hemd",
              "description": "Mohr im Hemd",
              "price": "4,50 €"
            },
            {
              "name": "Wunschpizza",
              "description": "Wunschpizza\r\nmit 4 Zutaten nach Wahl\r\nWahl aus: mit Ananas, mit Artischocken, mit Blattspinat, mit Bolognese, mit Broccoli und mehr.",
              "price": "11,70 €"
            }
          ]
        },
        "Salate": {
          "categoryName": "Salate",
          "categoryDescription": "",
          "items": [
            {
              "name": "Gemischter Salat",
              "description": "Gemischter Salat\r\nmit grünem Salat, Tomaten, Paprika, Zwiebeln und Joghurt-Dressing",
              "price": "6,00 €"
            },
            {
              "name": "Griechischer Salat",
              "description": "Griechischer Salat\r\ngemischter Salat mit Schafskäse, Oliven und Joghurt-Dressing",
              "price": "7,00 €"
            },
            {
              "name": "Thunfisch Salat",
              "description": "Thunfisch Salat\r\ngemischter Salat mit Thunfisch und Joghurt-Dressing",
              "price": "7,00 €"
            }
          ]
        },
        "Pizza aus dem Holzofen, Ø 33cm": {
          "categoryName": "Pizza aus dem Holzofen, Ø 33cm",
          "categoryDescription": "Alle Pizzen werden mit Tomatensauce, Käse und Oregano zubereitet.",
          "items": [
            {
              "name": "Pizza Margherita",
              "description": "Pizza Margherita\r\nWahl aus: mit Ananas, mit Artischocken, mit Blattspinat, mit Bolognese, mit Broccoli und mehr.",
              "price": "9,90 €"
            },
            {
              "name": "Pizza Prosciutto",
              "description": "Pizza Prosciutto\r\nmit Schinken\r\nWahl aus: mit Ananas, mit Artischocken, mit Blattspinat, mit Bolognese, mit Broccoli und mehr.",
              "price": "10,40 €"
            },
            {
              "name": "Pizza Rucola",
              "description": "Pizza Rucola\r\nmit Rucola und Tomatenscheiben\r\nWahl aus: mit Ananas, mit Artischocken, mit Blattspinat, mit Bolognese, mit Broccoli und mehr.",
              "price": "11,00 €"
            }
          ]
        },
        "Pasta": {
          "categoryName": "Pasta",
          "categoryDescription": "",
          "items": [
            {
              "name": "Spaghetti Bolognese",
              "description": "Spaghetti Bolognese\r\nmit Fleischsauce",
              "price": "9,90 €"
            },
            {
              "name": "Spaghetti Carbonara",
              "description": "Spaghetti Carbonara\r\nmit Schinken, Speck und Sahne",
              "price": "9,90 €"
            },
            {
              "name": "Spaghetti mit Gorgonzolasauce",
              "description": "Spaghetti mit Gorgonzolasauce",
              "price": "9,90 €"
            }
          ]
        },
        "Gefüllte Stangerl": {
          "categoryName": "Gefüllte Stangerl",
          "categoryDescription": "Alle Gerichte werden mit Tomatensauce und Käse zubereitet.",
          "items": [
            {
              "name": "Tonno-Stangerl",
              "description": "Tonno-Stangerl\r\nmit Thunfisch, Zwiebeln und Knoblauch\r\nWahl aus: mit Ananas, mit Artischocken, mit Blattspinat, mit Bolognese, mit Broccoli und mehr.",
              "price": "10,40 €"
            },
            {
              "name": "Salami-Stangerl",
              "description": "Salami-Stangerl\r\nmit Salami, Mais und Knoblauch\r\nWahl aus: mit Ananas, mit Artischocken, mit Blattspinat, mit Bolognese, mit Broccoli und mehr.",
              "price": "10,40 €"
            },
            {
              "name": "Schinken-Stangerl",
              "description": "Schinken-Stangerl\r\nmit Schinken, Mais und Knoblauch\r\nWahl aus: mit Ananas, mit Artischocken, mit Blattspinat, mit Bolognese, mit Broccoli und mehr.",
              "price": "10,40 €"
            }
          ]
        },
        "Fleischgerichte": {
          "categoryName": "Fleischgerichte",
          "categoryDescription": "",
          "items": [
            {
              "name": "Wiener Schnitzel",
              "description": "Wiener Schnitzel\r\ngebackenes Putenfleisch mit Salat und Pommes frites",
              "price": "10,90 €"
            },
            {
              "name": "Cordon Bleu",
              "description": "Cordon Bleu\r\nmit Salat und Pommes frites",
              "price": "10,90 €"
            },
            {
              "name": "Chicken Nuggets",
              "description": "Chicken Nuggets\r\nmit Pommes frites",
              "price": "10,90 €"
            }
          ]
        },
        "Pide": {
          "categoryName": "Pide",
          "categoryDescription": "Alle Pide werden mit Tomatensauce und Käse zubereitet.",
          "items": [
            {
              "name": "Pide Titanic",
              "description": "Pide Titanic\r\nmit Schinken, Speck, Pfefferoni, Ei, Oregano und Knoblauch\r\nWahl aus: mit Belag, doppelt und mit Joghurtsauce.",
              "price": "11,00 €"
            },
            {
              "name": "Pide a la Kurdi",
              "description": "Pide a la Kurdi\r\nmit Spinat, Schafskäse und Ei\r\nWahl aus: mit Belag, doppelt und mit Joghurtsauce.",
              "price": "11,00 €"
            }
          ]
        },
        "Snacks": {
          "categoryName": "Snacks",
          "categoryDescription": "",
          "items": [
            {
              "name": "Mozzarella Sticks",
              "description": "Mozzarella Sticks",
              "price": "9,90 €"
            },
            {
              "name": "Leere-Stangerl",
              "description": "Leere-Stangerl\r\nmit Joghurtsauce",
              "price": "3,50 €"
            },
            {
              "name": "Pommes frites",
              "description": "Pommes frites",
              "price": "4,50 €"
            }
          ]
        },
        "Ben & Jerry's": {
          "categoryName": "Ben & Jerry's",
          "categoryDescription": "",
          "items": [
            {
              "name": "Ben & Jerry's Cookie Dough 465ml",
              "description": "Ben & Jerry's Cookie Dough 465ml\r\nVanille-Eiscreme mit Riesenstücken aus Plätzchenteig und leckeren kakaohaltigen Bits.\r\n8,40 €",
              "price": "18,06 €/l, 465ml"
            },
            {
              "name": "Ben & Jerry's Caramel Brownie Party 465ml",
              "description": "Ben & Jerry's Caramel Brownie Party 465ml\r\n8,40 €",
              "price": "18,06 €/l, 465ml"
            },
            {
              "name": "Ben & Jerry's Chocolate Fudge Brownie 465ml",
              "description": "Ben & Jerry's Chocolate Fudge Brownie 465ml\r\nSündhaft cremige Schokoladen-Eiscreme mit saftigen Schokogebäck-Stücken.\r\n8,40 €",
              "price": "18,06 €/l, 465ml"
            }
          ]
        },
        "Nachspeisen": {
          "categoryName": "Nachspeisen",
          "categoryDescription": "",
          "items": [
            {
              "name": "Tiramisu",
              "description": "Tiramisu",
              "price": "4,50 €"
            },
            {
              "name": "Mohr im Hemd",
              "description": "Mohr im Hemd",
              "price": "4,50 €"
            },
            {
              "name": "Palatschinken mit Topfen",
              "description": "Palatschinken mit Topfen",
              "price": "4,80 €"
            }
          ]
        }
      }
    },
    {
      "index": 7,
      "link": "https://www.lieferando.at/speisekarte/pizza-di-roma",
      "i": 6,
      "name": "Pizza Di Roma",
      "logo": "https://res.cloudinary.com/tkwy-prod-eu/image/upload/c_thumb,h_120,w_176/f_auto/q_auto/v1672549360/static-takeaway-com/images/restaurants/at/57N5773/logo_465x320",
      "info": [
        "Adresse",
        "Eggenfelder str. 34",
        "8101 Gratkorn",
        "Momentan keine Lieferung"
      ],
      "meals": {
        "Beliebt": {
          "categoryName": "Beliebt",
          "categoryDescription": "popular meals",
          "items": [
            {
              "name": "Wunschpizza",
              "description": "Wunschpizza\r\nmit 4 Zutaten nach Wahl\r\nWahl aus: mit Artischocken, mit Broccoli, mit Champignons, mit Ei, mit Gorgonzola und mehr.",
              "price": "9,90 €"
            },
            {
              "name": "Pizza Margherita",
              "description": "Pizza Margherita\r\nmit frischem Basilikum\r\nWahl aus: mit Artischocken, mit Broccoli, mit Champignons, mit Ei, mit Gorgonzola und mehr.",
              "price": "9,90 €"
            },
            {
              "name": "Vegetarischer Burger",
              "description": "Vegetarischer Burger\r\nmit Gemüselaibchen, Salat und Tomaten\r\nWahl aus: mit Amerikanischer Sauce, mit Barbecuesauce, mit Chili-Knoblauchsauce, mit Chilisauce, mit Ketchup und mehr.",
              "price": "6,00 €"
            }
          ]
        },
        "Vorspeisen": {
          "categoryName": "Vorspeisen",
          "categoryDescription": "",
          "items": [
            {
              "name": "Mozzarella",
              "description": "Mozzarella\r\nmit Mozzarella und Tomatenscheiben",
              "price": "6,50 €"
            },
            {
              "name": "Italiana",
              "description": "Italiana\r\nmit grünem Salat, San Daniele, Mais, Balsamico, Rucola und Parmesan",
              "price": "7,50 €"
            },
            {
              "name": "Pizzabrot",
              "description": "Pizzabrot",
              "price": "3,00 €"
            }
          ]
        },
        "Frische Insalate": {
          "categoryName": "Frische Insalate",
          "categoryDescription": "Alle Salate werden mit einem Dressing nach Wahl serviert.",
          "items": [
            {
              "name": "Insalata Verde",
              "description": "Insalata Verde\r\ngrüner Salat\r\nWahl aus: mit Joghurt-Dressing, hausgemacht, mit Knoblauch-Dressing, mit Sonnenblumenöl oder ohne Dressing.",
              "price": "4,50 €"
            },
            {
              "name": "Insalata Mista",
              "description": "Insalata Mista\r\ngemischter Salat mit Tomaten, Paprika, Karotten und Zwiebeln\r\nWahl aus: mit Joghurt-Dressing, hausgemacht, mit Knoblauch-Dressing, mit Sonnenblumenöl oder ohne Dressing.",
              "price": "5,50 €"
            },
            {
              "name": "Insalata di Patate",
              "description": "Insalata di Patate\r\nKartoffelsalat\r\nWahl aus: mit Joghurt-Dressing, hausgemacht, mit Knoblauch-Dressing, mit Sonnenblumenöl oder ohne Dressing.",
              "price": "4,50 €"
            }
          ]
        },
        "Pizza, Ø 33cm (vegetarisch)": {
          "categoryName": "Pizza, Ø 33cm (vegetarisch)",
          "categoryDescription": "Alle Pizzen werden mit Tomatensauce, Käse und Oregano zubereitet.",
          "items": [
            {
              "name": "Pizza Margherita",
              "description": "Pizza Margherita\r\nmit frischem Basilikum\r\nWahl aus: mit Artischocken, mit Broccoli, mit Champignons, mit Ei, mit Gorgonzola und mehr.",
              "price": "9,90 €"
            },
            {
              "name": "Pizza Camillo",
              "description": "Pizza Camillo\r\nmit Schafskäse, Spinat und Ei\r\nWahl aus: mit Artischocken, mit Broccoli, mit Champignons, mit Ei, mit Gorgonzola und mehr.",
              "price": "10,90 €"
            },
            {
              "name": "Pizza Funghi",
              "description": "Pizza Funghi\r\nmit Champignons\r\nWahl aus: mit Artischocken, mit Broccoli, mit Champignons, mit Ei, mit Gorgonzola und mehr.",
              "price": "10,90 €"
            }
          ]
        },
        "Pizza, Ø 40cm (vegetarisch)": {
          "categoryName": "Pizza, Ø 40cm (vegetarisch)",
          "categoryDescription": "Alle Pizzen werden mit Tomatensauce, Käse und Oregano zubereitet.",
          "items": [
            {
              "name": "Pizza Margherita",
              "description": "Pizza Margherita\r\nmit frischem Basilikum\r\nWahl aus: mit Artischocken, mit Broccoli, mit Champignons, mit Ei, mit Gorgonzola und mehr.",
              "price": "15,50 €"
            },
            {
              "name": "Pizza Camillo",
              "description": "Pizza Camillo\r\nmit Schafskäse, Spinat und Ei\r\nWahl aus: mit Artischocken, mit Broccoli, mit Champignons, mit Ei, mit Gorgonzola und mehr.",
              "price": "15,50 €"
            },
            {
              "name": "Pizza Funghi",
              "description": "Pizza Funghi\r\nmit Champignons und Oregano\r\nWahl aus: mit Artischocken, mit Broccoli, mit Champignons, mit Ei, mit Gorgonzola und mehr.",
              "price": "15,50 €"
            }
          ]
        },
        "Pizza, Ø 33cm (Fisch)": {
          "categoryName": "Pizza, Ø 33cm (Fisch)",
          "categoryDescription": "Alle Pizzen werden mit Tomatensauce, Käse und Oregano zubereitet.",
          "items": [
            {
              "name": "Pizza al Tonno",
              "description": "Pizza al Tonno\r\nmit Thunfisch und Zwiebeln\r\nWahl aus: mit Artischocken, mit Broccoli, mit Champignons, mit Ei, mit Gorgonzola und mehr.",
              "price": "11,50 €"
            },
            {
              "name": "Pizza Frutti di Mare",
              "description": "Pizza Frutti di Mare\r\nmit Meeresfrüchten, Knoblauch und Oliven\r\nWahl aus: mit Artischocken, mit Broccoli, mit Champignons, mit Ei, mit Gorgonzola und mehr.",
              "price": "11,50 €"
            },
            {
              "name": "Pizza Romana",
              "description": "Pizza Romana\r\nmit Thunfisch, Champignons, Ei und Pfefferoni\r\nWahl aus: mit Artischocken, mit Broccoli, mit Champignons, mit Ei, mit Gorgonzola und mehr.",
              "price": "11,50 €"
            }
          ]
        },
        "Pizza, Ø 40cm (Fisch)": {
          "categoryName": "Pizza, Ø 40cm (Fisch)",
          "categoryDescription": "Alle Pizzen werden mit Tomatensauce, Käse und Oregano zubereitet.",
          "items": [
            {
              "name": "Pizza al Tonno",
              "description": "Pizza al Tonno\r\nmit Thunfisch und Zwiebeln\r\nWahl aus: mit Artischocken, mit Broccoli, mit Champignons, mit Ei, mit Gorgonzola und mehr.",
              "price": "17,50 €"
            },
            {
              "name": "Pizza Frutti di Mare",
              "description": "Pizza Frutti di Mare\r\nmit Meeresfrüchten, Knoblauch und Oliven\r\nWahl aus: mit Artischocken, mit Broccoli, mit Champignons, mit Ei, mit Gorgonzola und mehr.",
              "price": "17,50 €"
            },
            {
              "name": "Pizza Romana",
              "description": "Pizza Romana\r\nmit Thunfisch, Champignons, Ei und Pfefferoni\r\nWahl aus: mit Artischocken, mit Broccoli, mit Champignons, mit Ei, mit Gorgonzola und mehr.",
              "price": "17,50 €"
            }
          ]
        },
        "Pizza, Ø 33cm (Fleisch)": {
          "categoryName": "Pizza, Ø 33cm (Fleisch)",
          "categoryDescription": "Alle Pizzen werden mit Tomatensauce, Käse und Oregano zubereitet.",
          "items": [
            {
              "name": "Pizza Salami",
              "description": "Pizza Salami\r\nmit Salami\r\nWahl aus: mit Artischocken, mit Broccoli, mit Champignons, mit Ei, mit Gorgonzola und mehr.",
              "price": "10,90 €"
            },
            {
              "name": "Pizza Cardinale",
              "description": "Pizza Cardinale\r\nmit Schinken und Champignons\r\nWahl aus: mit Artischocken, mit Broccoli, mit Champignons, mit Ei, mit Gorgonzola und mehr.",
              "price": "11,50 €"
            },
            {
              "name": "Pizza Napoli",
              "description": "Pizza Napoli\r\nmit scharfer Salami\r\nWahl aus: mit Artischocken, mit Broccoli, mit Champignons, mit Ei, mit Gorgonzola und mehr.",
              "price": "11,50 €"
            }
          ]
        },
        "Pizza, Ø 40cm (Fleisch)": {
          "categoryName": "Pizza, Ø 40cm (Fleisch)",
          "categoryDescription": "Alle Pizzen werden mit Tomatensauce, Käse und Oregano zubereitet.",
          "items": [
            {
              "name": "Pizza Salami",
              "description": "Pizza Salami\r\nmit Salami\r\nWahl aus: mit Artischocken, mit Broccoli, mit Champignons, mit Ei, mit Gorgonzola und mehr.",
              "price": "16,50 €"
            },
            {
              "name": "Pizza Cardinale",
              "description": "Pizza Cardinale\r\nmit Schinken und Champignons\r\nWahl aus: mit Artischocken, mit Broccoli, mit Champignons, mit Ei, mit Gorgonzola und mehr.",
              "price": "16,50 €"
            },
            {
              "name": "Pizza Napoli",
              "description": "Pizza Napoli\r\nmit scharfer Salami\r\nWahl aus: mit Artischocken, mit Broccoli, mit Champignons, mit Ei, mit Gorgonzola und mehr.",
              "price": "16,50 €"
            }
          ]
        },
        "Calzone": {
          "categoryName": "Calzone",
          "categoryDescription": "Alle Calzoni werden mit Tomatensauce, Käse und Oregano zubereitet.",
          "items": [
            {
              "name": "Calzone Margherita",
              "description": "Calzone Margherita\r\nmit frischem Basilikum\r\nWahl aus: mit Artischocken, mit Broccoli, mit Champignons, mit Ei, mit Gorgonzola und mehr.",
              "price": "11,50 €"
            },
            {
              "name": "Calzone Camillo",
              "description": "Calzone Camillo\r\nmit Schafskäse, Spinat und Ei\r\nWahl aus: mit Artischocken, mit Broccoli, mit Champignons, mit Ei, mit Gorgonzola und mehr.",
              "price": "11,50 €"
            },
            {
              "name": "Calzone Funghi",
              "description": "Calzone Funghi\r\nmit Champignons und Oregano\r\nWahl aus: mit Artischocken, mit Broccoli, mit Champignons, mit Ei, mit Gorgonzola und mehr.",
              "price": "11,50 €"
            }
          ]
        },
        "Pizzastangerl": {
          "categoryName": "Pizzastangerl",
          "categoryDescription": "",
          "items": [
            {
              "name": "Salami-Stangerl",
              "description": "Salami-Stangerl\r\nmit Salami\r\nWahl aus: mit Artischocken, mit Broccoli, mit Champignons, mit Ei, mit Gorgonzola und mehr.",
              "price": "8,90 €"
            },
            {
              "name": "Spinaci-Stangerl",
              "description": "Spinaci-Stangerl\r\nmit Spinat und Schafskäse\r\nWahl aus: mit Artischocken, mit Broccoli, mit Champignons, mit Ei, mit Gorgonzola und mehr.",
              "price": "8,90 €"
            },
            {
              "name": "Schinken-Stangerl",
              "description": "Schinken-Stangerl\r\nmit Schinken und Champignons\r\nWahl aus: mit Artischocken, mit Broccoli, mit Champignons, mit Ei, mit Gorgonzola und mehr.",
              "price": "8,90 €"
            }
          ]
        },
        "Pasta": {
          "categoryName": "Pasta",
          "categoryDescription": "",
          "items": [
            {
              "name": "Spaghetti Parmigiano",
              "description": "Spaghetti Parmigiano\r\nmit Prosciutto, Parmesan, Spinat und Sahne",
              "price": "10,50 €"
            },
            {
              "name": "Spaghetti Spinaci",
              "description": "Spaghetti Spinaci\r\nmit Spinat und Sahne",
              "price": "10,50 €"
            },
            {
              "name": "Spaghetti Carbonara",
              "description": "Spaghetti Carbonara\r\nmit Speck und Sahne",
              "price": "10,50 €"
            }
          ]
        },
        "Hauptspeisen": {
          "categoryName": "Hauptspeisen",
          "categoryDescription": "",
          "items": [
            {
              "name": "Wienerschnitzel vom Schwein",
              "description": "Wienerschnitzel vom Schwein\r\nmit Pommes frites",
              "price": "10,20 €"
            },
            {
              "name": "Cordon Bleu vom Schwein",
              "description": "Cordon Bleu vom Schwein\r\ndazu Pommes frites",
              "price": "11,20 €"
            },
            {
              "name": "Cordon Bleu von der Pute",
              "description": "Cordon Bleu von der Pute\r\ndazu Pommes frites",
              "price": "11,20 €"
            }
          ]
        },
        "Fischgerichte": {
          "categoryName": "Fischgerichte",
          "categoryDescription": "",
          "items": [
            {
              "name": "Calamari fritti",
              "description": "Calamari fritti\r\nmit Sauce Tartare und Pommes frites",
              "price": "8,70 €"
            }
          ]
        },
        "Burger und mehr": {
          "categoryName": "Burger und mehr",
          "categoryDescription": "Alle Burger werden mit 100% Rindfleisch und mit einer Sauce nach Wahl zubereitet.",
          "items": [
            {
              "name": "Hamburger",
              "description": "Hamburger\r\nmit Salat und Essiggurke\r\nWahl aus: mit Amerikanischer Sauce, mit Barbecuesauce, mit Chili-Knoblauchsauce, mit Chilisauce, mit Ketchup und mehr.",
              "price": "6,00 €"
            },
            {
              "name": "Cheeseburger",
              "description": "Cheeseburger\r\nmit Salat, Käse und Essiggurke\r\nWahl aus: mit Amerikanischer Sauce, mit Barbecuesauce, mit Chili-Knoblauchsauce, mit Chilisauce, mit Ketchup und mehr.",
              "price": "6,50 €"
            },
            {
              "name": "Double Burger",
              "description": "Double Burger\r\nmit doppelt Fleisch, Salat, Essiggurke und Bacon\r\nWahl aus: mit Amerikanischer Sauce, mit Barbecuesauce, mit Chili-Knoblauchsauce, mit Chilisauce, mit Ketchup und mehr.",
              "price": "7,50 €"
            }
          ]
        },
        "Burger Menü": {
          "categoryName": "Burger Menü",
          "categoryDescription": "",
          "items": [
            {
              "name": "Burger mit Pommes frites",
              "description": "Burger mit Pommes frites\r\n• 1 Burger mit 1 Fleischlaibchen nach Wahl\r\n• 1 Pommes frites\r\n• Sauce nach Wahl\r\n• 1 Getränk 0,33l nach Wahl\r\nWahl aus: Hamburger, Cheeseburger, Royal Burger, Wunsch Burger, Steirischer Burger und mehr.",
              "price": "12,50 €"
            },
            {
              "name": "Burger mit kleinen gemischten Salat",
              "description": "Burger mit kleinen gemischten Salat\r\n• 1 Burger mit 2 Fleischlaibchen nach Wahl • 1 Pommes frites\r\n• 1 Salat\r\n• Sauce nach Wahl\r\n• 1 Getränk 0,33l nach Wahl\r\nWahl aus: Hamburger, Cheeseburger, Double Burger, Double Cheeseburger, Royal Burger und mehr.",
              "price": "14,50 €"
            }
          ]
        },
        "Beilagen - Saucen": {
          "categoryName": "Beilagen - Saucen",
          "categoryDescription": "",
          "items": [
            {
              "name": "Pommes frites",
              "description": "Pommes frites",
              "price": "4,00 €"
            },
            {
              "name": "Bratkartoffeln",
              "description": "Bratkartoffeln",
              "price": "4,00 €"
            },
            {
              "name": "Potato Wedges",
              "description": "Potato Wedges",
              "price": "4,50 €"
            }
          ]
        },
        "Desserts": {
          "categoryName": "Desserts",
          "categoryDescription": "",
          "items": [
            {
              "name": "Hausgemachtes Tiramisu",
              "description": "Hausgemachtes Tiramisu",
              "price": "4,90 €"
            },
            {
              "name": "Profiteroles",
              "description": "Profiteroles",
              "price": "4,90 €"
            },
            {
              "name": "Donuts",
              "description": "Donuts\r\nmit Zutat nach Wahl\r\nWahl aus: mit Schokolade, mit Vanille oder ohne Zutat.",
              "price": "3,50 €"
            }
          ]
        }
      }
    }
  ]
}